{
  "TaskInstancesStore": [
    {
      "name": "task_0",
      "initialOffset": 0,
      "value": [
        {
          "instance": 0,
          "periodStartTime": 0,
          "letStartTime": 0,
          "letEndTime": 49,
          "periodEndTime": 1000000,
          "executionTime": 49,
          "executionIntervals": [
            {
              "startTime": 0,
              "endTime": 49,
              "core": "c0"
            }
          ],
          "currentCore": {
            "name": "c0",
            "speedup": 1
          }
        }
      ]
    },
    {
      "name": "task_2",
      "initialOffset": 0,
      "value": [
        {
          "instance": 0,
          "periodStartTime": 0,
          "letStartTime": 49,
          "letEndTime": 60,
          "periodEndTime": 1000000,
          "executionTime": 11,
          "executionIntervals": [
            {
              "startTime": 49,
              "endTime": 60,
              "core": "c2"
            }
          ],
          "currentCore": {
            "name": "c2",
            "speedup": 1
          }
        }
      ]
    },
    {
      "name": "task_4",
      "initialOffset": 0,
      "value": [
        {
          "instance": 0,
          "periodStartTime": 0,
          "letStartTime": 49,
          "letEndTime": 50,
          "periodEndTime": 1000000,
          "executionTime": 1,
          "executionIntervals": [
            {
              "startTime": 49,
              "endTime": 50,
              "core": "c4"
            }
          ],
          "currentCore": {
            "name": "c4",
            "speedup": 1
          }
        }
      ]
    },
    {
      "name": "task_5",
      "initialOffset": 0,
      "value": [
        {
          "instance": 0,
          "periodStartTime": 0,
          "letStartTime": 64,
          "letEndTime": 97,
          "periodEndTime": 1000000,
          "executionTime": 33,
          "executionIntervals": [
            {
              "startTime": 64,
              "endTime": 97,
              "core": "c4"
            }
          ],
          "currentCore": {
            "name": "c4",
            "speedup": 1
          }
        }
      ]
    },
    {
      "name": "task_6",
      "initialOffset": 0,
      "value": [
        {
          "instance": 0,
          "periodStartTime": 0,
          "letStartTime": 52,
          "letEndTime": 65,
          "periodEndTime": 1000000,
          "executionTime": 13,
          "executionIntervals": [
            {
              "startTime": 52,
              "endTime": 65,
              "core": "c0"
            }
          ],
          "currentCore": {
            "name": "c0",
            "speedup": 1
          }
        }
      ]
    },
    {
      "name": "task_7",
      "initialOffset": 0,
      "value": [
        {
          "instance": 0,
          "periodStartTime": 0,
          "letStartTime": 80,
          "letEndTime": 97,
          "periodEndTime": 1000000,
          "executionTime": 17,
          "executionIntervals": [
            {
              "startTime": 80,
              "endTime": 97,
              "core": "c0"
            }
          ],
          "currentCore": {
            "name": "c0",
            "speedup": 1
          }
        }
      ]
    },
    {
      "name": "task_1",
      "initialOffset": 0,
      "value": [
        {
          "instance": 0,
          "periodStartTime": 0,
          "letStartTime": 54,
          "letEndTime": 64,
          "periodEndTime": 1000000,
          "executionTime": 10,
          "executionIntervals": [
            {
              "startTime": 54,
              "endTime": 64,
              "core": "c4"
            }
          ],
          "currentCore": {
            "name": "c4",
            "speedup": 1
          }
        }
      ]
    },
    {
      "name": "task_3",
      "initialOffset": 0,
      "value": [
        {
          "instance": 0,
          "periodStartTime": 0,
          "letStartTime": 49,
          "letEndTime": 99,
          "periodEndTime": 1000000,
          "executionTime": 50,
          "executionIntervals": [
            {
              "startTime": 49,
              "endTime": 99,
              "core": "c1"
            }
          ],
          "currentCore": {
            "name": "c1",
            "speedup": 1
          }
        }
      ]
    },
    {
      "name": "task_11",
      "initialOffset": 0,
      "value": [
        {
          "instance": 0,
          "periodStartTime": 0,
          "letStartTime": 107,
          "letEndTime": 159,
          "periodEndTime": 1000000,
          "executionTime": 52,
          "executionIntervals": [
            {
              "startTime": 107,
              "endTime": 159,
              "core": "c6"
            }
          ],
          "currentCore": {
            "name": "c6",
            "speedup": 1
          }
        }
      ]
    },
    {
      "name": "task_12",
      "initialOffset": 0,
      "value": [
        {
          "instance": 0,
          "periodStartTime": 0,
          "letStartTime": 100,
          "letEndTime": 143,
          "periodEndTime": 1000000,
          "executionTime": 43,
          "executionIntervals": [
            {
              "startTime": 100,
              "endTime": 143,
              "core": "c4"
            }
          ],
          "currentCore": {
            "name": "c4",
            "speedup": 1
          }
        }
      ]
    },
    {
      "name": "task_13",
      "initialOffset": 0,
      "value": [
        {
          "instance": 0,
          "periodStartTime": 0,
          "letStartTime": 105,
          "letEndTime": 159,
          "periodEndTime": 1000000,
          "executionTime": 54,
          "executionIntervals": [
            {
              "startTime": 105,
              "endTime": 159,
              "core": "c7"
            }
          ],
          "currentCore": {
            "name": "c7",
            "speedup": 1
          }
        }
      ]
    },
    {
      "name": "task_8",
      "initialOffset": 0,
      "value": [
        {
          "instance": 0,
          "periodStartTime": 0,
          "letStartTime": 97,
          "letEndTime": 100,
          "periodEndTime": 1000000,
          "executionTime": 3,
          "executionIntervals": [
            {
              "startTime": 97,
              "endTime": 100,
              "core": "c4"
            }
          ],
          "currentCore": {
            "name": "c4",
            "speedup": 1
          }
        }
      ]
    },
    {
      "name": "task_9",
      "initialOffset": 0,
      "value": [
        {
          "instance": 0,
          "periodStartTime": 0,
          "letStartTime": 65,
          "letEndTime": 93,
          "periodEndTime": 1000000,
          "executionTime": 28,
          "executionIntervals": [
            {
              "startTime": 65,
              "endTime": 93,
              "core": "c6"
            }
          ],
          "currentCore": {
            "name": "c6",
            "speedup": 1
          }
        }
      ]
    },
    {
      "name": "task_14",
      "initialOffset": 0,
      "value": [
        {
          "instance": 0,
          "periodStartTime": 0,
          "letStartTime": 143,
          "letEndTime": 159,
          "periodEndTime": 1000000,
          "executionTime": 16,
          "executionIntervals": [
            {
              "startTime": 143,
              "endTime": 159,
              "core": "c4"
            }
          ],
          "currentCore": {
            "name": "c4",
            "speedup": 1
          }
        }
      ]
    },
    {
      "name": "task_15",
      "initialOffset": 0,
      "value": [
        {
          "instance": 0,
          "periodStartTime": 0,
          "letStartTime": 99,
          "letEndTime": 159,
          "periodEndTime": 1000000,
          "executionTime": 60,
          "executionIntervals": [
            {
              "startTime": 99,
              "endTime": 159,
              "core": "c2"
            }
          ],
          "currentCore": {
            "name": "c2",
            "speedup": 1
          }
        }
      ]
    },
    {
      "name": "task_10",
      "initialOffset": 0,
      "value": [
        {
          "instance": 0,
          "periodStartTime": 0,
          "letStartTime": 65,
          "letEndTime": 105,
          "periodEndTime": 1000000,
          "executionTime": 40,
          "executionIntervals": [
            {
              "startTime": 65,
              "endTime": 105,
              "core": "c7"
            }
          ],
          "currentCore": {
            "name": "c7",
            "speedup": 1
          }
        }
      ]
    },
    {
      "name": "task_19",
      "initialOffset": 0,
      "value": [
        {
          "instance": 0,
          "periodStartTime": 0,
          "letStartTime": 159,
          "letEndTime": 179,
          "periodEndTime": 1000000,
          "executionTime": 20,
          "executionIntervals": [
            {
              "startTime": 159,
              "endTime": 179,
              "core": "c4"
            }
          ],
          "currentCore": {
            "name": "c4",
            "speedup": 1
          }
        }
      ]
    },
    {
      "name": "task_20",
      "initialOffset": 0,
      "value": [
        {
          "instance": 0,
          "periodStartTime": 0,
          "letStartTime": 162,
          "letEndTime": 219,
          "periodEndTime": 1000000,
          "executionTime": 57,
          "executionIntervals": [
            {
              "startTime": 162,
              "endTime": 219,
              "core": "c7"
            }
          ],
          "currentCore": {
            "name": "c7",
            "speedup": 1
          }
        }
      ]
    },
    {
      "name": "task_17",
      "initialOffset": 0,
      "value": [
        {
          "instance": 0,
          "periodStartTime": 0,
          "letStartTime": 179,
          "letEndTime": 209,
          "periodEndTime": 1000000,
          "executionTime": 30,
          "executionIntervals": [
            {
              "startTime": 179,
              "endTime": 209,
              "core": "c4"
            }
          ],
          "currentCore": {
            "name": "c4",
            "speedup": 1
          }
        }
      ]
    },
    {
      "name": "task_18",
      "initialOffset": 0,
      "value": [
        {
          "instance": 0,
          "periodStartTime": 0,
          "letStartTime": 159,
          "letEndTime": 216,
          "periodEndTime": 1000000,
          "executionTime": 57,
          "executionIntervals": [
            {
              "startTime": 159,
              "endTime": 216,
              "core": "c6"
            }
          ],
          "currentCore": {
            "name": "c6",
            "speedup": 1
          }
        }
      ]
    },
    {
      "name": "task_21",
      "initialOffset": 0,
      "value": [
        {
          "instance": 0,
          "periodStartTime": 0,
          "letStartTime": 159,
          "letEndTime": 219,
          "periodEndTime": 1000000,
          "executionTime": 60,
          "executionIntervals": [
            {
              "startTime": 159,
              "endTime": 219,
              "core": "c2"
            }
          ],
          "currentCore": {
            "name": "c2",
            "speedup": 1
          }
        }
      ]
    },
    {
      "name": "task_22",
      "initialOffset": 0,
      "value": [
        {
          "instance": 0,
          "periodStartTime": 0,
          "letStartTime": 143,
          "letEndTime": 182,
          "periodEndTime": 1000000,
          "executionTime": 39,
          "executionIntervals": [
            {
              "startTime": 143,
              "endTime": 182,
              "core": "c1"
            }
          ],
          "currentCore": {
            "name": "c1",
            "speedup": 1
          }
        }
      ]
    },
    {
      "name": "task_16",
      "initialOffset": 0,
      "value": [
        {
          "instance": 0,
          "periodStartTime": 0,
          "letStartTime": 216,
          "letEndTime": 231,
          "periodEndTime": 1000000,
          "executionTime": 15,
          "executionIntervals": [
            {
              "startTime": 216,
              "endTime": 231,
              "core": "c6"
            }
          ],
          "currentCore": {
            "name": "c6",
            "speedup": 1
          }
        }
      ]
    },
    {
      "name": "task_26",
      "initialOffset": 0,
      "value": [
        {
          "instance": 0,
          "periodStartTime": 0,
          "letStartTime": 242,
          "letEndTime": 272,
          "periodEndTime": 1000000,
          "executionTime": 30,
          "executionIntervals": [
            {
              "startTime": 242,
              "endTime": 272,
              "core": "c7"
            }
          ],
          "currentCore": {
            "name": "c7",
            "speedup": 1
          }
        }
      ]
    },
    {
      "name": "task_23",
      "initialOffset": 0,
      "value": [
        {
          "instance": 0,
          "periodStartTime": 0,
          "letStartTime": 231,
          "letEndTime": 272,
          "periodEndTime": 1000000,
          "executionTime": 41,
          "executionIntervals": [
            {
              "startTime": 231,
              "endTime": 272,
              "core": "c6"
            }
          ],
          "currentCore": {
            "name": "c6",
            "speedup": 1
          }
        }
      ]
    },
    {
      "name": "task_24",
      "initialOffset": 0,
      "value": [
        {
          "instance": 0,
          "periodStartTime": 0,
          "letStartTime": 230,
          "letEndTime": 272,
          "periodEndTime": 1000000,
          "executionTime": 42,
          "executionIntervals": [
            {
              "startTime": 230,
              "endTime": 272,
              "core": "c0"
            }
          ],
          "currentCore": {
            "name": "c0",
            "speedup": 1
          }
        }
      ]
    },
    {
      "name": "task_27",
      "initialOffset": 0,
      "value": [
        {
          "instance": 0,
          "periodStartTime": 0,
          "letStartTime": 219,
          "letEndTime": 272,
          "periodEndTime": 1000000,
          "executionTime": 53,
          "executionIntervals": [
            {
              "startTime": 219,
              "endTime": 272,
              "core": "c2"
            }
          ],
          "currentCore": {
            "name": "c2",
            "speedup": 1
          }
        }
      ]
    },
    {
      "name": "task_25",
      "initialOffset": 0,
      "value": [
        {
          "instance": 0,
          "periodStartTime": 0,
          "letStartTime": 228,
          "letEndTime": 272,
          "periodEndTime": 1000000,
          "executionTime": 44,
          "executionIntervals": [
            {
              "startTime": 228,
              "endTime": 272,
              "core": "c4"
            }
          ],
          "currentCore": {
            "name": "c4",
            "speedup": 1
          }
        }
      ]
    },
    {
      "name": "task_28",
      "initialOffset": 0,
      "value": [
        {
          "instance": 0,
          "periodStartTime": 0,
          "letStartTime": 219,
          "letEndTime": 236,
          "periodEndTime": 1000000,
          "executionTime": 17,
          "executionIntervals": [
            {
              "startTime": 219,
              "endTime": 236,
              "core": "c1"
            }
          ],
          "currentCore": {
            "name": "c1",
            "speedup": 1
          }
        }
      ]
    },
    {
      "name": "task_29",
      "initialOffset": 0,
      "value": [
        {
          "instance": 0,
          "periodStartTime": 0,
          "letStartTime": 272,
          "letEndTime": 287,
          "periodEndTime": 1000000,
          "executionTime": 15,
          "executionIntervals": [
            {
              "startTime": 272,
              "endTime": 287,
              "core": "c7"
            }
          ],
          "currentCore": {
            "name": "c7",
            "speedup": 1
          }
        }
      ]
    }
  ]
}