{
  "TaskInstancesStore": [
    {
      "name": "task_0",
      "initialOffset": 0,
      "value": [
        {
          "instance": 0,
          "periodStartTime": 0,
          "letStartTime": 0,
          "letEndTime": 89,
          "periodEndTime": 998001,
          "executionTime": 89,
          "executionIntervals": [
            {
              "startTime": 0,
              "endTime": 89,
              "core": "c0"
            }
          ],
          "currentCore": {
            "name": "c0",
            "speedup": 1
          }
        }
      ]
    },
    {
      "name": "task_2",
      "initialOffset": 0,
      "value": [
        {
          "instance": 0,
          "periodStartTime": 0,
          "letStartTime": 89,
          "letEndTime": 162,
          "periodEndTime": 998001,
          "executionTime": 73,
          "executionIntervals": [
            {
              "startTime": 89,
              "endTime": 162,
              "core": "c4"
            }
          ],
          "currentCore": {
            "name": "c4",
            "speedup": 1
          }
        }
      ]
    },
    {
      "name": "task_4",
      "initialOffset": 0,
      "value": [
        {
          "instance": 0,
          "periodStartTime": 0,
          "letStartTime": 89,
          "letEndTime": 124,
          "periodEndTime": 998001,
          "executionTime": 35,
          "executionIntervals": [
            {
              "startTime": 89,
              "endTime": 124,
              "core": "c3"
            }
          ],
          "currentCore": {
            "name": "c3",
            "speedup": 1
          }
        }
      ]
    },
    {
      "name": "task_5",
      "initialOffset": 0,
      "value": [
        {
          "instance": 0,
          "periodStartTime": 0,
          "letStartTime": 162,
          "letEndTime": 168,
          "periodEndTime": 998001,
          "executionTime": 6,
          "executionIntervals": [
            {
              "startTime": 162,
              "endTime": 168,
              "core": "c4"
            }
          ],
          "currentCore": {
            "name": "c4",
            "speedup": 1
          }
        }
      ]
    },
    {
      "name": "task_1",
      "initialOffset": 0,
      "value": [
        {
          "instance": 0,
          "periodStartTime": 0,
          "letStartTime": 89,
          "letEndTime": 165,
          "periodEndTime": 998001,
          "executionTime": 76,
          "executionIntervals": [
            {
              "startTime": 89,
              "endTime": 165,
              "core": "c5"
            }
          ],
          "currentCore": {
            "name": "c5",
            "speedup": 1
          }
        }
      ]
    },
    {
      "name": "task_3",
      "initialOffset": 0,
      "value": [
        {
          "instance": 0,
          "periodStartTime": 0,
          "letStartTime": 89,
          "letEndTime": 162,
          "periodEndTime": 998001,
          "executionTime": 73,
          "executionIntervals": [
            {
              "startTime": 89,
              "endTime": 162,
              "core": "c0"
            }
          ],
          "currentCore": {
            "name": "c0",
            "speedup": 1
          }
        }
      ]
    },
    {
      "name": "task_7",
      "initialOffset": 0,
      "value": [
        {
          "instance": 0,
          "periodStartTime": 0,
          "letStartTime": 165,
          "letEndTime": 254,
          "periodEndTime": 998001,
          "executionTime": 89,
          "executionIntervals": [
            {
              "startTime": 165,
              "endTime": 254,
              "core": "c1"
            }
          ],
          "currentCore": {
            "name": "c1",
            "speedup": 1
          }
        }
      ]
    },
    {
      "name": "task_8",
      "initialOffset": 0,
      "value": [
        {
          "instance": 0,
          "periodStartTime": 0,
          "letStartTime": 168,
          "letEndTime": 188,
          "periodEndTime": 998001,
          "executionTime": 20,
          "executionIntervals": [
            {
              "startTime": 168,
              "endTime": 188,
              "core": "c0"
            }
          ],
          "currentCore": {
            "name": "c0",
            "speedup": 1
          }
        }
      ]
    },
    {
      "name": "task_6",
      "initialOffset": 0,
      "value": [
        {
          "instance": 0,
          "periodStartTime": 0,
          "letStartTime": 188,
          "letEndTime": 249,
          "periodEndTime": 998001,
          "executionTime": 61,
          "executionIntervals": [
            {
              "startTime": 188,
              "endTime": 249,
              "core": "c0"
            }
          ],
          "currentCore": {
            "name": "c0",
            "speedup": 1
          }
        }
      ]
    },
    {
      "name": "task_9",
      "initialOffset": 0,
      "value": [
        {
          "instance": 0,
          "periodStartTime": 0,
          "letStartTime": 266,
          "letEndTime": 300,
          "periodEndTime": 998001,
          "executionTime": 34,
          "executionIntervals": [
            {
              "startTime": 266,
              "endTime": 300,
              "core": "c4"
            }
          ],
          "currentCore": {
            "name": "c4",
            "speedup": 1
          }
        }
      ]
    },
    {
      "name": "task_11",
      "initialOffset": 0,
      "value": [
        {
          "instance": 0,
          "periodStartTime": 0,
          "letStartTime": 254,
          "letEndTime": 358,
          "periodEndTime": 998001,
          "executionTime": 104,
          "executionIntervals": [
            {
              "startTime": 254,
              "endTime": 358,
              "core": "c2"
            }
          ],
          "currentCore": {
            "name": "c2",
            "speedup": 1
          }
        }
      ]
    },
    {
      "name": "task_14",
      "initialOffset": 0,
      "value": [
        {
          "instance": 0,
          "periodStartTime": 0,
          "letStartTime": 249,
          "letEndTime": 266,
          "periodEndTime": 998001,
          "executionTime": 17,
          "executionIntervals": [
            {
              "startTime": 249,
              "endTime": 266,
              "core": "c4"
            }
          ],
          "currentCore": {
            "name": "c4",
            "speedup": 1
          }
        }
      ]
    },
    {
      "name": "task_15",
      "initialOffset": 0,
      "value": [
        {
          "instance": 0,
          "periodStartTime": 0,
          "letStartTime": 254,
          "letEndTime": 329,
          "periodEndTime": 998001,
          "executionTime": 75,
          "executionIntervals": [
            {
              "startTime": 254,
              "endTime": 329,
              "core": "c5"
            }
          ],
          "currentCore": {
            "name": "c5",
            "speedup": 1
          }
        }
      ]
    },
    {
      "name": "task_10",
      "initialOffset": 0,
      "value": [
        {
          "instance": 0,
          "periodStartTime": 0,
          "letStartTime": 359,
          "letEndTime": 364,
          "periodEndTime": 998001,
          "executionTime": 5,
          "executionIntervals": [
            {
              "startTime": 359,
              "endTime": 364,
              "core": "c0"
            }
          ],
          "currentCore": {
            "name": "c0",
            "speedup": 1
          }
        }
      ]
    },
    {
      "name": "task_12",
      "initialOffset": 0,
      "value": [
        {
          "instance": 0,
          "periodStartTime": 0,
          "letStartTime": 254,
          "letEndTime": 352,
          "periodEndTime": 998001,
          "executionTime": 98,
          "executionIntervals": [
            {
              "startTime": 254,
              "endTime": 352,
              "core": "c0"
            }
          ],
          "currentCore": {
            "name": "c0",
            "speedup": 1
          }
        }
      ]
    },
    {
      "name": "task_13",
      "initialOffset": 0,
      "value": [
        {
          "instance": 0,
          "periodStartTime": 0,
          "letStartTime": 254,
          "letEndTime": 314,
          "periodEndTime": 998001,
          "executionTime": 60,
          "executionIntervals": [
            {
              "startTime": 254,
              "endTime": 314,
              "core": "c1"
            }
          ],
          "currentCore": {
            "name": "c1",
            "speedup": 1
          }
        }
      ]
    },
    {
      "name": "task_16",
      "initialOffset": 0,
      "value": [
        {
          "instance": 0,
          "periodStartTime": 0,
          "letStartTime": 358,
          "letEndTime": 386,
          "periodEndTime": 998001,
          "executionTime": 28,
          "executionIntervals": [
            {
              "startTime": 358,
              "endTime": 386,
              "core": "c5"
            }
          ],
          "currentCore": {
            "name": "c5",
            "speedup": 1
          }
        }
      ]
    },
    {
      "name": "task_18",
      "initialOffset": 0,
      "value": [
        {
          "instance": 0,
          "periodStartTime": 0,
          "letStartTime": 355,
          "letEndTime": 386,
          "periodEndTime": 998001,
          "executionTime": 31,
          "executionIntervals": [
            {
              "startTime": 355,
              "endTime": 386,
              "core": "c3"
            }
          ],
          "currentCore": {
            "name": "c3",
            "speedup": 1
          }
        }
      ]
    },
    {
      "name": "task_17",
      "initialOffset": 0,
      "value": [
        {
          "instance": 0,
          "periodStartTime": 0,
          "letStartTime": 364,
          "letEndTime": 386,
          "periodEndTime": 998001,
          "executionTime": 22,
          "executionIntervals": [
            {
              "startTime": 364,
              "endTime": 386,
              "core": "c0"
            }
          ],
          "currentCore": {
            "name": "c0",
            "speedup": 1
          }
        }
      ]
    },
    {
      "name": "task_19",
      "initialOffset": 0,
      "value": [
        {
          "instance": 0,
          "periodStartTime": 0,
          "letStartTime": 386,
          "letEndTime": 389,
          "periodEndTime": 998001,
          "executionTime": 3,
          "executionIntervals": [
            {
              "startTime": 386,
              "endTime": 389,
              "core": "c0"
            }
          ],
          "currentCore": {
            "name": "c0",
            "speedup": 1
          }
        }
      ]
    }
  ]
}